{"meta":{"name":"OLD RELEASES","id":"Flow216","type":"channel","posterShape":"landscape","videos":[{"id":"Flow2stream_16_0","title":"...And Justice for All (1979)"},{"id":"Flow2stream_16_1","title":"01 A Nightmare On Elm Street - Horror 1984 Eng Subs 720p [H264-mp4]"},{"id":"Flow2stream_16_2","title":"01 Childs Play - Chucky Horror Eng 720p [H264-mp4]"},{"id":"Flow2stream_16_3","title":"01 Halloween - Horror 1978 Donald Pleasence Eng Subs 720p [H264-mp4]"},{"id":"Flow2stream_16_4","title":"1. The Terminator (1984) KartiKing Movies.DigitalMaza.Org"},{"id":"Flow2stream_16_5","title":"02 A Nightmare On Elm Street 2 Freddys Revenge - Horror 1985 Eng Subs 720p [H264-mp4]"},{"id":"Flow2stream_16_6","title":"02 Childs Play 2 - Chucky Horror Eng 720p [H264-mp4]"},{"id":"Flow2stream_16_7","title":"02 Halloween II - Horror 1981 Donald Pleasence Eng Subs 720p [H264-mp4]"},{"id":"Flow2stream_16_8","title":"2 Guns (2013)"},{"id":"Flow2stream_16_9","title":"03 A Nightmare On Elm Street 3 Dream Warriors - Horror 1987 Eng Subs 720p [H264-mp4]"},{"id":"Flow2stream_16_10","title":"03 Childs Play 3 - Chucky Horror Eng 720p [H264-mp4]"},{"id":"Flow2stream_16_11","title":"03 Halloween III Season of the Witch - Horror 1982 Eng Subs 720p [H264-mp4]"},{"id":"Flow2stream_16_12","title":"04 A Nightmare On Elm Street 4 The Dream Master - Horror 1988 Eng Subs 720p [h264-mp4]-1"},{"id":"Flow2stream_16_13","title":"04 Bride of Chucky - Chucky Horror Eng 720p [H264-mp4]"},{"id":"Flow2stream_16_14","title":"04 Halloween 4 The Return of Michael Myers - Horror 1988 Donald Pleasence Eng Subs 720p [H264-mp4]"},{"id":"Flow2stream_16_15","title":"05 A Nightmare On Elm Street 5 The Dream Child - Horror 1989 Eng Subs 720p [H264-mp4]"},{"id":"Flow2stream_16_16","title":"05 Halloween 5 The Revenge of Michael Myers - Horror 1989 Donald Pleasence Eng Subs 720p [H264-mp4]"},{"id":"Flow2stream_16_17","title":"05 Seed of Chucky - Chucky Horror Eng 720p [H264-mp4]"},{"id":"Flow2stream_16_18","title":"06 Curse of Chucky - Chucky Horror Eng 720p [H264-mp4]"},{"id":"Flow2stream_16_19","title":"06 Freddys Dead The Final Nightmare - Horror 1991 Eng Subs 720p [H264-mp4]"},{"id":"Flow2stream_16_20","title":"06 Halloween The Curse of Michael Myers - Horror 1995 Donald Pleasence Eng Subs 720p [H264-mp4]"},{"id":"Flow2stream_16_21","title":"07 Halloween H20 20 Years Later - Horror 1998 Eng Subs 720p [H264-mp4]"},{"id":"Flow2stream_16_22","title":"07 Wes Cravens New Nightmare - Horror 1994 Eng Subs 720p [H264-mp4]"},{"id":"Flow2stream_16_23","title":"08 Freddy VS Jason - Horror 2003 Eng Subs 720p [H264-mp4]"},{"id":"Flow2stream_16_24","title":"08 Halloween Resurrection - Horror 2002 Eng Subs 720p [H264-mp4]"},{"id":"Flow2stream_16_25","title":"09 A Nightmare On Elm Street - Horror 2010 Eng Subs 720p [H264-mp4]"},{"id":"Flow2stream_16_26","title":"09 Halloween Rob Zombie - Horror 2007 Eng Subs 720p [H264-mp4]"},{"id":"Flow2stream_16_27","title":"10 Halloween II Rob Zombie - Horror 2009 Eng Subs 720p [H264-mp4]"},{"id":"Flow2stream_16_28","title":"12 Strong (2018)"},{"id":"Flow2stream_16_29","title":"20th Century Women (2016)"},{"id":"Flow2stream_16_30","title":"21 Jump Street (2012)"},{"id":"Flow2stream_16_31","title":"24 Hours to Live (2017)"},{"id":"Flow2stream_16_32","title":"47 Meters Down (2017)"},{"id":"Flow2stream_16_33","title":"50 First Dates (2004)"},{"id":"Flow2stream_16_34","title":"1922.2017.720p.BluRay.x264-[YTS.AG]"},{"id":"Flow2stream_16_35","title":"A-X-L (2018)"},{"id":"Flow2stream_16_36","title":"A Bad Moms Christmas (2017)"},{"id":"Flow2stream_16_37","title":"A Man Apart (2003)"},{"id":"Flow2stream_16_38","title":"Above the Rim (1994)"},{"id":"Flow2stream_16_39","title":"Ace Ventura: Pet Detective (1994)"},{"id":"Flow2stream_16_40","title":"Ace Ventura: When Nature Calls (1995)"},{"id":"Flow2stream_16_41","title":"Acrimony (2018)"},{"id":"Flow2stream_16_42","title":"After Earth (2013)"},{"id":"Flow2stream_16_43","title":"Airheads (1994)"},{"id":"Flow2stream_16_44","title":"Alex Cross (2012)"},{"id":"Flow2stream_16_45","title":"Ali (2001)"},{"id":"Flow2stream_16_46","title":"Alien: Covenant (2017)"},{"id":"Flow2stream_16_47","title":"Alien 3 Special Edition 1992.720p.BrRip.x264.YIFY"},{"id":"Flow2stream_16_48","title":"Alien Director's Cut 1979.720p.BrRip.x264.YIFY"},{"id":"Flow2stream_16_49","title":"Aliens Special Edition 1986.720p.BrRip.x264.YIFY"},{"id":"Flow2stream_16_50","title":"All Eyez on Me (2017)"},{"id":"Flow2stream_16_51","title":"All I See Is You (2016)"},{"id":"Flow2stream_16_52","title":"All the Money in the World (2017)"},{"id":"Flow2stream_16_53","title":"Alpha (2018)"},{"id":"Flow2stream_16_54","title":"American Made (2017)"},{"id":"Flow2stream_16_55","title":"American Pie 2 (2001)"},{"id":"Flow2stream_16_56","title":"American.Pie.7-Presents.The.Book.of.Love.720p.x264.YIFY"},{"id":"Flow2stream_16_57","title":"American Pie (1999)"},{"id":"Flow2stream_16_58","title":"American Pie Presents: Band Camp (2005)"},{"id":"Flow2stream_16_59","title":"American Pie Presents: Beta House (2007)"},{"id":"Flow2stream_16_60","title":"American Pie Presents: The Naked Mile (2006)"},{"id":"Flow2stream_16_61","title":"American Gangster (2007)"},{"id":"Flow2stream_16_62","title":"American Pie 3 - The Wedding.YIFY"},{"id":"Flow2stream_16_63","title":"Amityville: The Awakening (2017)"},{"id":"Flow2stream_16_64","title":"Anchorman 2: The Legend Continues (2013)"},{"id":"Flow2stream_16_65","title":"Anchorman: The Legend of Ron Burgundy (2004)"},{"id":"Flow2stream_16_66","title":"Anger Managment.2003.720p.BrRip.x264.YIFY"},{"id":"Flow2stream_16_67","title":"Annabelle (2014)"},{"id":"Flow2stream_16_68","title":"Annabelle: Creation (2017)"},{"id":"Flow2stream_16_69","title":"Annihilation (2018)"},{"id":"Flow2stream_16_70","title":"Ant-Man and the Wasp (2018)"},{"id":"Flow2stream_16_71","title":"Ant-Man (2015)"},{"id":"Flow2stream_16_72","title":"Antidote (2018)"},{"id":"Flow2stream_16_73","title":"Any Given Sunday (1999)"},{"id":"Flow2stream_16_74","title":"Apostle (2018)"},{"id":"Flow2stream_16_75","title":"A Quiet Place (2018)"},{"id":"Flow2stream_16_76","title":"Argo (2012)"},{"id":"Flow2stream_16_77","title":"ATL (2006)"},{"id":"Flow2stream_16_78","title":"Avatar.ECE.2009.720p.BrRip.x264.bitloks.YIFY"},{"id":"Flow2stream_16_79","title":"Avengers: Age of Ultron (2015)"},{"id":"Flow2stream_16_80","title":"Baby Boy (2001)"},{"id":"Flow2stream_16_81","title":"Back to the Future (1985)"},{"id":"Flow2stream_16_82","title":"Back to the Future Part II (1989)"},{"id":"Flow2stream_16_83","title":"Back to the Future Part III (1990)"},{"id":"Flow2stream_16_84","title":"Batman v Superman: Dawn of Justice (2016)"},{"id":"Flow2stream_16_85","title":"Battle of the Sexes (2017)"},{"id":"Flow2stream_16_86","title":"Battleship (2012)"},{"id":"Flow2stream_16_87","title":"Baywatch (2017)"},{"id":"Flow2stream_16_88","title":"Beast of Burden (2018)"},{"id":"Flow2stream_16_89","title":"Bedtime Stories (2008)"},{"id":"Flow2stream_16_90","title":"belly2-xvid"},{"id":"Flow2stream_16_91","title":"belly 1998720p"},{"id":"Flow2stream_16_92","title":"Beneath the Planet of the Apes (1970)"},{"id":"Flow2stream_16_93","title":"Better Watch Out (2016)"},{"id":"Flow2stream_16_94","title":"Beverly Hills Cop (1984)"},{"id":"Flow2stream_16_95","title":"Beverly Hills Ninja  [x264ac3][Bubanee]"},{"id":"Flow2stream_16_96","title":"Beyond Skyline (2017)"},{"id":"Flow2stream_16_97","title":"Big Momma's House (2000)"},{"id":"Flow2stream_16_98","title":"Biker Boyz (2003)"},{"id":"Flow2stream_16_99","title":"Billy Madison (1995)"},{"id":"Flow2stream_16_100","title":"Biohazard.Patient.Zero.2012.720p.BluRay.x264.YIFY"},{"id":"Flow2stream_16_101","title":"Black Panther (2018)"},{"id":"Flow2stream_16_102","title":"Black Butterfly (2017)"},{"id":"Flow2stream_16_103","title":"Blade (1998)"},{"id":"Flow2stream_16_104","title":"Blade II (2002)"},{"id":"Flow2stream_16_105","title":"Blade: Trinity (2004)"},{"id":"Flow2stream_16_106","title":"Blended (2014)"},{"id":"Flow2stream_16_107","title":"Bon Cop Bad Cop 2 (2017)"},{"id":"Flow2stream_16_108","title":"Boo! A Madea Halloween (2016)"},{"id":"Flow2stream_16_109","title":"Boogie Nights (1997)"},{"id":"Flow2stream_16_110","title":"Boondock.Saints.Director's.Cut.1999.1080p.BrRip.x264.YIFY"},{"id":"Flow2stream_16_111","title":"Boyz n the Hood (1991)"},{"id":"Flow2stream_16_112","title":"Brad's Status (2017)"},{"id":"Flow2stream_16_113","title":"Brawl in Cell Block 99 (2017)"},{"id":"Flow2stream_16_114","title":"Bridge of Spies (2015)"},{"id":"Flow2stream_16_115","title":"Bright (2017)"},{"id":"Flow2stream_16_116","title":"Brooklyn (2015)"},{"id":"Flow2stream_16_117","title":"Bullet (1996)"},{"id":"Flow2stream_16_118","title":"Bullet Head (2017)"},{"id":"Flow2stream_16_119","title":"Captain America: Civil War (2016)"},{"id":"Flow2stream_16_120","title":"Captain America: The Winter Soldier (2014)"},{"id":"Flow2stream_16_121","title":"Carlito's Way (1993)"},{"id":"Flow2stream_16_122","title":"Carol (2015)"},{"id":"Flow2stream_16_123","title":"Case39.2009.720p.BrRip.x264.YIFY"},{"id":"Flow2stream_16_124","title":"Casino (1995)"},{"id":"Flow2stream_16_125","title":"Central Intelligence (2016)"},{"id":"Flow2stream_16_126","title":"Chalet Girl (2011)"},{"id":"Flow2stream_16_127","title":"Cherry Falls (2000)"},{"id":"Flow2stream_16_128","title":"Children of Men (2006)"},{"id":"Flow2stream_16_129","title":"Children of the Corn: Runaway (2018)"},{"id":"Flow2stream_16_130","title":"Cinderella (2015)"},{"id":"Flow2stream_16_131","title":"Click (2006)"},{"id":"Flow2stream_16_132","title":"Cliffhanger (1993)"},{"id":"Flow2stream_16_133","title":"Cloverfield (2008)"},{"id":"Flow2stream_16_134","title":"Cobra (1986)"},{"id":"Flow2stream_16_135","title":"Collateral Beauty (2016)"},{"id":"Flow2stream_16_136","title":"Coming to America (1988)"},{"id":"Flow2stream_16_137","title":"Concussion (2015)"},{"id":"Flow2stream_16_138","title":"Conquest of the Planet of the Apes (1972)"},{"id":"Flow2stream_16_139","title":"Creed (2015)"},{"id":"Flow2stream_16_140","title":"Creep 2 (2017)"},{"id":"Flow2stream_16_141","title":"Crimson Peak (2015)"},{"id":"Flow2stream_16_142","title":"Crimson Tide (1995)"},{"id":"Flow2stream_16_143","title":"Cruising (1980)"},{"id":"Flow2stream_16_144","title":"Cult of Chucky (2017)"},{"id":"Flow2stream_16_145","title":"Cursed (2005)"},{"id":"Flow2stream_16_146","title":"Daddy's Home 2 (2017)"},{"id":"Flow2stream_16_147","title":"Daddy's Home (2015)"},{"id":"Flow2stream_16_148","title":"Daddy's Little Girls (2007)"},{"id":"Flow2stream_16_149","title":"Danny Collins (2015)"},{"id":"Flow2stream_16_150","title":"Dark Tide (2012)"},{"id":"Flow2stream_16_151","title":"Darkness Falls (2003)"},{"id":"Flow2stream_16_152","title":"Dawn of the Planet of the Apes (2014)"},{"id":"Flow2stream_16_153","title":"Deadly Switch (2019)"},{"id":"Flow2stream_16_154","title":"Deadpool (2016)"},{"id":"Flow2stream_16_155","title":"Dear.Dictator.2017.1080p.BluRay.x264-[YTS.AM]"},{"id":"Flow2stream_16_156","title":"Death.Race.3.Inferno.2012.UNRATED.WEBRip.XviD-BiDA"},{"id":"Flow2stream_16_157","title":"Deepwater Horizon (2016)"},{"id":"Flow2stream_16_158","title":"Delirium (2018)"},{"id":"Flow2stream_16_159","title":"Demolition Man (1993)"},{"id":"Flow2stream_16_160","title":"Den of Thieves (2018)"},{"id":"Flow2stream_16_161","title":"Deuce Bigalow: European Gigolo (2005)"},{"id":"Flow2stream_16_162","title":"Deuce Bigalow: Male Gigolo (1999)"},{"id":"Flow2stream_16_163","title":"Diary of a Mad Black Woman (2005)"},{"id":"Flow2stream_16_164","title":"Diary of a Mad Black Woman (2005)"},{"id":"Flow2stream_16_165","title":"Diary of a Wimpy Kid: The Long Haul (2017)"},{"id":"Flow2stream_16_166","title":"Dirty Grandpa (2016)"},{"id":"Flow2stream_16_167","title":"Disturbia (2007)"},{"id":"Flow2stream_16_168","title":"Divergent (2014)"},{"id":"Flow2stream_16_169","title":"Doctor Strange (2016)"},{"id":"Flow2stream_16_170","title":"Dog Day Afternoon (1975)"},{"id":"Flow2stream_16_171","title":"Don't Breathe (2016)"},{"id":"Flow2stream_16_172","title":"done-killer.joe"},{"id":"Flow2stream_16_173","title":"Donnie Brasco (1997)"},{"id":"Flow2stream_16_174","title":"Down a Dark Hall (2018)"},{"id":"Flow2stream_16_175","title":"Downsizing (2017)"},{"id":"Flow2stream_16_176","title":"Dracula Untold (2014)"},{"id":"Flow2stream_16_177","title":"Drag.Me.To.Hell.Unrated.2009.720p.BrRip.x264.YIFY"},{"id":"Flow2stream_16_178","title":"Drive (2011)"},{"id":"Flow2stream_16_179","title":"Early Man (2018)"},{"id":"Flow2stream_16_180","title":"Eastern Promises (2007)"},{"id":"Flow2stream_16_181","title":"Edge of Tomorrow (2014)"},{"id":"Flow2stream_16_182","title":"Elle (2016)"},{"id":"Flow2stream_16_183","title":"Elysium (2013)"},{"id":"Flow2stream_16_184","title":"End of Watch (2012)"},{"id":"Flow2stream_16_185","title":"Enemy of the State (1998)"},{"id":"Flow2stream_16_186","title":"Escape from Planet Earth - 2013"},{"id":"Flow2stream_16_187","title":"Escape from the Planet of the Apes (1971)"},{"id":"Flow2stream_16_188","title":"Escape Plan (2013)"},{"id":"Flow2stream_16_189","title":"Eurotrip.UNRATED.DVDRiP.XViD-DEiTY"},{"id":"Flow2stream_16_190","title":"Everest (2015)"},{"id":"Flow2stream_16_191","title":"Everybody Wants Some!! (2016)"},{"id":"Flow2stream_16_192","title":"Eyes of an Angel (1991)"},{"id":"Flow2stream_16_193","title":"Fallen (2016)"},{"id":"Flow2stream_16_194","title":"Fantastic Beasts and Where to Find Them (2016)"},{"id":"Flow2stream_16_195","title":"Fast & Furious (2009)"},{"id":"Flow2stream_16_196","title":"Fast and Furious 5 Fast Five (2011) DVDRip XviD-MAXSPEED www.torentz.3xforum.ro"},{"id":"Flow2stream_16_197","title":"Father Figures (2017)"},{"id":"Flow2stream_16_198","title":"Fences (2016)"},{"id":"Flow2stream_16_199","title":"Fifty Shades of Grey (2015)"},{"id":"Flow2stream_16_200","title":"Final Destination (2000)"},{"id":"Flow2stream_16_201","title":"Final Destination 2 (2003)"},{"id":"Flow2stream_16_202","title":"Final Destination 3 (2006)"},{"id":"Flow2stream_16_203","title":"The Final Destination (2009)"},{"id":"Flow2stream_16_204","title":"Final Destination 5 (2011)"},{"id":"Flow2stream_16_205","title":"First Kill (2017)"},{"id":"Flow2stream_16_206","title":"Fist Fight (2017)"},{"id":"Flow2stream_16_207","title":"Focus (2015)"},{"id":"Flow2stream_16_208","title":"Four Brothers (2005)"},{"id":"Flow2stream_16_209","title":"Friday (1995)"},{"id":"Flow2stream_16_210","title":"Friday the 13th (2009)"},{"id":"Flow2stream_16_211","title":"Friday the 13th: A New Beginning (1985)"},{"id":"Flow2stream_16_212","title":"Friday the 13th Part III (1982)"},{"id":"Flow2stream_16_213","title":"Friday the 13th Part VII: The New Blood (1988)"},{"id":"Flow2stream_16_214","title":"Friday the 13th Part VIII: Jason Takes Manhattan (1989)"},{"id":"Flow2stream_16_215","title":"Friday the 13th: The Final Chapter (1984)"},{"id":"Flow2stream_16_216","title":"Friday After Next (2002)"},{"id":"Flow2stream_16_217","title":"Fright Night (2011)"},{"id":"Flow2stream_16_218","title":"Funny People (2009)"},{"id":"Flow2stream_16_219","title":"Furious.Seven.2015.720p.BluRay.x264.YIFY"},{"id":"Flow2stream_16_220","title":"Game Night (2018)"},{"id":"Flow2stream_16_221","title":"Get Out (2017)"},{"id":"Flow2stream_16_222","title":"Ghost House (2017)"},{"id":"Flow2stream_16_223","title":"Ghostbusters (2016)"},{"id":"Flow2stream_16_224","title":"Girls Trip (2017)"},{"id":"Flow2stream_16_225","title":"Glory Road (2006)"},{"id":"Flow2stream_16_226","title":"Godzilla (2014)"},{"id":"Flow2stream_16_227","title":"Going in Style (2017)"},{"id":"Flow2stream_16_228","title":"Gone Girl (2014)"},{"id":"Flow2stream_16_229","title":"Good Will Hunting (1997)"},{"id":"Flow2stream_16_230","title":"GoodFellas (1990)"},{"id":"Flow2stream_16_231","title":"Goon: Last of the Enforcers (2017)"},{"id":"Flow2stream_16_232","title":"Gotti (2018)"},{"id":"Flow2stream_16_233","title":"Green Lantern (2011)"},{"id":"Flow2stream_16_234","title":"Gridiron Gang (2006)"},{"id":"Flow2stream_16_235","title":"Gringo (2018)"},{"id":"Flow2stream_16_236","title":"Grown Ups 2 (2013)"},{"id":"Flow2stream_16_237","title":"Grown Ups (2010)"},{"id":"Flow2stream_16_238","title":"Guardians of the Galaxy (2014)"},{"id":"Flow2stream_16_239","title":"Guardians of the Galaxy Vol. 2 (2017)"},{"id":"Flow2stream_16_240","title":"Gun Shy (2017)"},{"id":"Flow2stream_16_241","title":" Caesar! (2016)"},{"id":"Flow2stream_16_242","title":"Hancock (2008)"},{"id":"Flow2stream_16_243","title":"Hangman (2017)"},{"id":"Flow2stream_16_244","title":"Happy Death Day (2017)"},{"id":"Flow2stream_16_245","title":"Happy Gilmore (1996)"},{"id":"Flow2stream_16_246","title":"Harry Potter and the Deathly Hallows: Part 1 (2010)"},{"id":"Flow2stream_16_247","title":"Harry Potter and the Deathly Hallows: Part 2 (2011)"},{"id":"Flow2stream_16_248","title":"Harry Potter and the Chamber of Secrets (2002)"},{"id":"Flow2stream_16_249","title":"Harry Potter and the Goblet of Fire (2005)"},{"id":"Flow2stream_16_250","title":"Harry Potter and the Half-Blood Prince (2009)"},{"id":"Flow2stream_16_251","title":"He Got Game (1998)"},{"id":"Flow2stream_16_252","title":"Heat (1995)"},{"id":"Flow2stream_16_253","title":"Hell or High Water (2016)"},{"id":"Flow2stream_16_254","title":"Hercules (2014)"},{"id":"Flow2stream_16_255","title":"Hickok (2017)"},{"id":"Flow2stream_16_256","title":"Hidden Figures (2016)"},{"id":"Flow2stream_16_257","title":"Hitch (2005)"},{"id":"Flow2stream_16_258","title":"Hole.In.One.2010.DVDRipx264.YIFY"},{"id":"Flow2stream_16_259","title":"House on Elm Lake (2017)"},{"id":"Flow2stream_16_260","title":"How High (2001)"},{"id":"Flow2stream_16_261","title":"How to Be a Latin Lover (2017)"},{"id":"Flow2stream_16_262","title":"Hulk (2003)"},{"id":"Flow2stream_16_263","title":"Hunt for the Wilderpeople (2016)"},{"id":"Flow2stream_16_264","title":"Hustle & Flow (2005)"},{"id":"Flow2stream_16_265","title":"I.Am.Legend.ALTERNATE.ENDING.2007.1080p.BrRip.x264.YIFY"},{"id":"Flow2stream_16_266","title":"I Know What You Did Last Summer (1997)"},{"id":"Flow2stream_16_267","title":" Robot (2004)"},{"id":"Flow2stream_16_268","title":"I Still Know What You Did Last Summer (1998)"},{"id":"Flow2stream_16_269","title":"i can do bad all by my self"},{"id":"Flow2stream_16_270","title":"Identity Theft (2007)"},{"id":"Flow2stream_16_271","title":"I'll Always Know What You Did Last Summer (2006)"},{"id":"Flow2stream_16_272","title":"In a Valley of Violence (2016)"},{"id":"Flow2stream_16_273","title":"In the Fade (2017)"},{"id":"Flow2stream_16_274","title":"Inception (2010)"},{"id":"Flow2stream_16_275","title":"Independence Day: Resurgence (2016)"},{"id":"Flow2stream_16_276","title":"Independence Day (1996)"},{"id":"Flow2stream_16_277","title":"Inside Man (2006)"},{"id":"Flow2stream_16_278","title":"Insidious (2010)"},{"id":"Flow2stream_16_279","title":"Insidious: Chapter 2 (2013)"},{"id":"Flow2stream_16_280","title":"Insidious: Chapter 3 (2015)"},{"id":"Flow2stream_16_281","title":"Insidious: The Last Key (2018)"},{"id":"Flow2stream_16_282","title":"Insomnia (2002)"},{"id":"Flow2stream_16_283","title":"Interstellar (2014)"},{"id":"Flow2stream_16_284","title":"I Spit on Your Grave (2010)"},{"id":"Flow2stream_16_285","title":"It (2017)"},{"id":"Flow2stream_16_286","title":"It Comes at Night (2017)"},{"id":"Flow2stream_16_287","title":"J. Edgar (2011)"},{"id":"Flow2stream_16_288","title":"Jack and Jill (2011)"},{"id":"Flow2stream_16_289","title":"Jackie (2016)"},{"id":"Flow2stream_16_290","title":"Jason Bourne (2016)"},{"id":"Flow2stream_16_291","title":"Jason Goes to Hell: The Final Friday (1993)"},{"id":"Flow2stream_16_292","title":"Jason.Lives.Friday.the.13th.Part.VI.1986.720p.BluRay.x264.YIFY"},{"id":"Flow2stream_16_293","title":"Jason X (2001)"},{"id":"Flow2stream_16_294","title":"Jeepers Creepers (2001)"},{"id":"Flow2stream_16_295","title":"Jeepers Creepers 3 (2017)"},{"id":"Flow2stream_16_296","title":"Jeepers Creepers 2 (2003)"},{"id":"Flow2stream_16_297","title":"Jennifer's.Body.UNRATED.2009.1080p.BrRip.x264.YIFY"},{"id":"Flow2stream_16_298","title":"Jigsaw (2017)"},{"id":"Flow2stream_16_299","title":"John Q (2002)"},{"id":"Flow2stream_16_300","title":"John Carter (2012)"},{"id":"Flow2stream_16_301","title":"Journey 2: The Mysterious Island (2012)"},{"id":"Flow2stream_16_302","title":"Juice.[Tupac][ENG]DvDrip[1992]-vestax"},{"id":"Flow2stream_16_303","title":"Jumanji: Welcome to the Jungle (2017)"},{"id":"Flow2stream_16_304","title":"Jurassic Park (1993)"},{"id":"Flow2stream_16_305","title":"The Lost World: Jurassic Park (1997)"},{"id":"Flow2stream_16_306","title":"Jurassic Park III (2001)"},{"id":"Flow2stream_16_307","title":"Jurassic World (2015)"},{"id":"Flow2stream_16_308","title":"Just Getting Started (2017)"},{"id":"Flow2stream_16_309","title":"Just Go with It (2011)"},{"id":"Flow2stream_16_310","title":"Keep Watching (2017)"},{"id":"Flow2stream_16_311","title":"Kidnapped (1960)"},{"id":"Flow2stream_16_312","title":"Killing Gunther (2017)"},{"id":"Flow2stream_16_313","title":"Killing Hasselhoff (2017)"},{"id":"Flow2stream_16_314","title":"Kill the Irishman (2011)"},{"id":"Flow2stream_16_315","title":"Kingsman: The Golden Circle (2017)"},{"id":"Flow2stream_16_316","title":"Knight and Day (2010)"},{"id":"Flow2stream_16_317","title":"Kong: Skull Island (2017)"},{"id":"Flow2stream_16_318","title":"Krampus (2015)"},{"id":"Flow2stream_16_319","title":"Krampus: The Devil Returns (2016)"},{"id":"Flow2stream_16_320","title":"La La Land (2016)"},{"id":"Flow2stream_16_321","title":"Lawless - Gangster [2012] [480p.BRRiP.X264-PTRG] [Lektor PL] [Arx]"},{"id":"Flow2stream_16_322","title":"Leatherface (2017)"},{"id":"Flow2stream_16_323","title":"Let the Right One In (2008)"},{"id":"Flow2stream_16_324","title":"Life (2017)"},{"id":"Flow2stream_16_325","title":"Life of Pi (2012)"},{"id":"Flow2stream_16_326","title":"Lights Out (2016)"},{"id":"Flow2stream_16_327","title":"Little Nicky (2000)"},{"id":"Flow2stream_16_328","title":"Lockout.UNRATED.BDRip.XviD-COCAIN"},{"id":"Flow2stream_16_329","title":"Look Away (2018)"},{"id":"Flow2stream_16_330","title":"Looper (2012)"},{"id":"Flow2stream_16_331","title":"Loveless (2017)"},{"id":"Flow2stream_16_332","title":"Mad Max: Fury Road (2015)"},{"id":"Flow2stream_16_333","title":"Madea's.Family.Reunion.(The.Play).2005"},{"id":"Flow2stream_16_334","title":"Madea's Witness Protection (2012)"},{"id":"Flow2stream_16_335","title":"Madea's Witness Protection (2012)"},{"id":"Flow2stream_16_336","title":"Maggie (2015)"},{"id":"Flow2stream_16_337","title":"Magic Mike XXL (2015)"},{"id":"Flow2stream_16_338","title":"Malcolm X (1992)"},{"id":"Flow2stream_16_339","title":"Malevolent (2018)"},{"id":"Flow2stream_16_340","title":"Man on Fire (2004)"},{"id":"Flow2stream_16_341","title":"Manchester by the Sea (2016)"},{"id":"Flow2stream_16_342","title":"Mandy (2018)"},{"id":"Flow2stream_16_343","title":"Mark Felt: The Man Who Brought Down the White House (2017)"},{"id":"Flow2stream_16_344","title":"Marrowbone (2017)"},{"id":"Flow2stream_16_345","title":"Marshall (2017)"},{"id":"Flow2stream_16_346","title":"Masterminds (2016)"},{"id":"Flow2stream_16_347","title":"Maximum Conviction (2012)"},{"id":"Flow2stream_16_348","title":"Maze Runner: The Scorch Trials (2015)"},{"id":"Flow2stream_16_349","title":"Maze Runner: The Death Cure (2018)"},{"id":"Flow2stream_16_350","title":"Men in Black 3 (2012)"},{"id":"Flow2stream_16_351","title":"Men in Black (1997)"},{"id":"Flow2stream_16_352","title":"Men in Black II (2002)"},{"id":"Flow2stream_16_353","title":"Midnight Special (2016)"},{"id":"Flow2stream_16_354","title":"Mistress America (2015)"},{"id":"Flow2stream_16_355","title":"Molly's Game (2017)"},{"id":"Flow2stream_16_356","title":"Moonlight (2016)"},{"id":"Flow2stream_16_357","title":"Mortal Engines (2018)"},{"id":"Flow2stream_16_358","title":"mother! (2017)"},{"id":"Flow2stream_16_359","title":"Mother Krampus (2017)"},{"id":"Flow2stream_16_360","title":"Mr. Deeds (2002)"},{"id":"Flow2stream_16_361","title":"My Bloody Valentine (2009)"},{"id":"Flow2stream_16_362","title":"Need for Speed (2014)"},{"id":"Flow2stream_16_363","title":"Next Friday (2000)"},{"id":"Flow2stream_16_364","title":"Nobody's Fool (2018)"},{"id":"Flow2stream_16_365","title":"Nocturnal Animals (2016)"},{"id":"Flow2stream_16_366","title":"Nothing but Trouble (1991)"},{"id":"Flow2stream_16_367","title":"November Criminals (2017)"},{"id":"Flow2stream_16_368","title":"Ocean's Eleven (2001)"},{"id":"Flow2stream_16_369","title":"Ocean's Thirteen (2007)"},{"id":"Flow2stream_16_370","title":"Ocean's Twelve (2004)"},{"id":"Flow2stream_16_371","title":"One Missed Call (2008)"},{"id":"Flow2stream_16_372","title":"Only Mine (2019)"},{"id":"Flow2stream_16_373","title":"Open.Water.3.Cage.Dive.2017.720p.BluRay.x264-[YTS.AG]"},{"id":"Flow2stream_16_374","title":"Orphan (2009)"},{"id":"Flow2stream_16_375","title":"Ouija (2014)"},{"id":"Flow2stream_16_376","title":"Ouija: Origin of Evil (2016)"},{"id":"Flow2stream_16_377","title":"Out of Time (2003)"},{"id":"Flow2stream_16_378","title":"Over the Top (1987)"},{"id":"Flow2stream_16_379","title":"Paid in Full (2002)"},{"id":"Flow2stream_16_380","title":"Pain & Gain (2013)"},{"id":"Flow2stream_16_381","title":"Pandorum (2009)"},{"id":"Flow2stream_16_382","title":"Passengers (2016)"},{"id":"Flow2stream_16_383","title":"Paterson (2016)"},{"id":"Flow2stream_16_384","title":"Patriots Day (2016)"},{"id":"Flow2stream_16_385","title":"Philadelphia (1993)"},{"id":"Flow2stream_16_386","title":"Piranha 3DD (2012)"},{"id":"Flow2stream_16_387","title":"Piranha 3D (2010)"},{"id":"Flow2stream_16_388","title":"Pirates of the Caribbean: At World's End (2007)"},{"id":"Flow2stream_16_389","title":"Pirates of the Caribbean: The Curse of the Black Pearl (2003)"},{"id":"Flow2stream_16_390","title":"Pirates of the Caribbean: Dead Man's Chest (2006)"},{"id":"Flow2stream_16_391","title":"Pirates of the Caribbean: Dead Men Tell No Tales (2017)"},{"id":"Flow2stream_16_392","title":"Pirates of the Caribbean: On Stranger Tides (2011)"},{"id":"Flow2stream_16_393","title":"Pitch Black (2000)"},{"id":"Flow2stream_16_394","title":"Pitch Perfect 2 (2015)"},{"id":"Flow2stream_16_395","title":"Pitch Perfect 3 (2017)"},{"id":"Flow2stream_16_396","title":"Pixels (2015)"},{"id":"Flow2stream_16_397","title":"Planet of the Apes (1968)"},{"id":"Flow2stream_16_398","title":"Poetic Justice (1993)"},{"id":"Flow2stream_16_399","title":"Police.Academy.2.1985.Their.First.Assignment"},{"id":"Flow2stream_16_400","title":"Police Academy (1984)"},{"id":"Flow2stream_16_401","title":"Police Academy (1984)"},{"id":"Flow2stream_16_402","title":"Police Academy (1984)"},{"id":"Flow2stream_16_403","title":"Prom Night (2008)"},{"id":"Flow2stream_16_404","title":"Prometheus (2012)"},{"id":"Flow2stream_16_405","title":"Proud Mary (2018)"},{"id":"Flow2stream_16_406","title":"psig-the.expendables.2.2012.r5.line.xvid"},{"id":"Flow2stream_16_407","title":"Pulp Fiction (1994)"},{"id":"Flow2stream_16_408","title":"Punch-Drunk Love (2002)"},{"id":"Flow2stream_16_409","title":"Quarantine (2008)"},{"id":"Flow2stream_16_410","title":"Rambo (2008)"},{"id":"Flow2stream_16_411","title":"Rambo First Blood Part I[1982]dvdrip[xvid Ac3[5.1]"},{"id":"Flow2stream_16_412","title":"Ready Player One (2018)"},{"id":"Flow2stream_16_413","title":"Red Sparrow (2018)"},{"id":"Flow2stream_16_414","title":"Reign Over Me (2007)"},{"id":"Flow2stream_16_415","title":"Remember the Titans (2000)"},{"id":"Flow2stream_16_416","title":"Resident Evil: The Final Chapter (2016)"},{"id":"Flow2stream_16_417","title":"Riddick (2013)"},{"id":"Flow2stream_16_418","title":"Righteous Kill (2008)"},{"id":"Flow2stream_16_419","title":"Rings (2017)"},{"id":"Flow2stream_16_420","title":"Rings (2017)"},{"id":"Flow2stream_16_421","title":"Rise of the Planet of the Apes (2011)"},{"id":"Flow2stream_16_422","title":"Road Trip (2000)"},{"id":"Flow2stream_16_423","title":"Rocky (1976)"},{"id":"Flow2stream_16_424","title":"Rocky Balboa (2006)"},{"id":"Flow2stream_16_425","title":"Rocky IV (1985)"},{"id":"Flow2stream_16_426","title":"Rocky V (1990)"},{"id":"Flow2stream_16_427","title":"Rogue.One.2016.720p.BluRay.x264-[YTS.AG]"},{"id":"Flow2stream_16_428","title":"Roll Bounce (2005)"},{"id":"Flow2stream_16_429","title":"Roman.J.Israel.Esq.2018.HDRip.XviD.AC3-EVO"},{"id":"Flow2stream_16_430","title":"Room (2015)"},{"id":"Flow2stream_16_431","title":"Rough Night (2017)"},{"id":"Flow2stream_16_432","title":"Rush Hour (1998)"},{"id":"Flow2stream_16_433","title":"Rush Hour 2 (2001)"},{"id":"Flow2stream_16_434","title":"Rush Hour 3 (2007)"},{"id":"Flow2stream_16_435","title":"s4a-assault.on.wall.street.2013.hdrip.xvid"},{"id":"Flow2stream_16_436","title":"Safe House (2012)"},{"id":"Flow2stream_16_437","title":"Same Kind of Different as Me (2017)"},{"id":"Flow2stream_16_438","title":"San Andreas (2015)"},{"id":"Flow2stream_16_439","title":"Sandy Wexler (2017)"},{"id":"Flow2stream_16_440","title":"Savage Dog (2017)"},{"id":"Flow2stream_16_441","title":"Saving Private Ryan (1998)"},{"id":"Flow2stream_16_442","title":"Scarface (1983)"},{"id":"Flow2stream_16_443","title":"Scary Movie (2000)"},{"id":"Flow2stream_16_444","title":"Scary Movie 2 (2001)"},{"id":"Flow2stream_16_445","title":"Scary Movie 3 (2003)"},{"id":"Flow2stream_16_446","title":"Scary Movie 4 (2006)"},{"id":"Flow2stream_16_447","title":"Scary Movie 5 (2013)"},{"id":"Flow2stream_16_448","title":"Scent of a Woman (1992)"},{"id":"Flow2stream_16_449","title":"Scream 4 (2011)"},{"id":"Flow2stream_16_450","title":"Scream 2 (1997)"},{"id":"Flow2stream_16_451","title":"Scream 3 (2000)"},{"id":"Flow2stream_16_452","title":"Scream (1996)"},{"id":"Flow2stream_16_453","title":"Semi.Pro.UNRATED.2008.720p.BrRip.x264.YIFY"},{"id":"Flow2stream_16_454","title":"Serpico (1973)"},{"id":"Flow2stream_16_455","title":"Seven Pounds (2008)"},{"id":"Flow2stream_16_456","title":"Shot Caller (2017)"},{"id":"Flow2stream_16_457","title":"Shottas (2002)"},{"id":"Flow2stream_16_458","title":"Sicario: Day of the Soldado (2018)"},{"id":"Flow2stream_16_459","title":"Silence (2016)"},{"id":"Flow2stream_16_460","title":"Silver Linings Playbook (2012)"},{"id":"Flow2stream_16_461","title":"Sing Street (2016)"},{"id":"Flow2stream_16_462","title":"Sinister (2012)"},{"id":"Flow2stream_16_463","title":"Skyscraper (2018)"},{"id":"Flow2stream_16_464","title":"Slumber (2017)"},{"id":"Flow2stream_16_465","title":"Snatched (2017)"},{"id":"Flow2stream_16_466","title":"Snitch (2013)"},{"id":"Flow2stream_16_467","title":"Solis (2018)"},{"id":"Flow2stream_16_468","title":"Solo: A Star Wars Story (2018)"},{"id":"Flow2stream_16_469","title":"Sonic the Hedgehog (2020)"},{"id":"Flow2stream_16_470","title":"Southpaw (2015)"},{"id":"Flow2stream_16_471","title":"Sparkle (2012)"},{"id":"Flow2stream_16_472","title":"Special Forces (2011)"},{"id":"Flow2stream_16_473","title":"Spectre (2015)"},{"id":"Flow2stream_16_474","title":"Spider-Man: Into the Spider-Verse (2018)"},{"id":"Flow2stream_16_475","title":"Splinter (2008)"},{"id":"Flow2stream_16_476","title":"Stand Up Guys (2012)"},{"id":"Flow2stream_16_477","title":"Star Trek Beyond (2016)"},{"id":"Flow2stream_16_478","title":"Star Wars: Episode I - The Phantom Menace (1999)"},{"id":"Flow2stream_16_479","title":"Star.Wars.Episode.4.A.New.Hope.1977.1080p.BrRip.x264.BOKUTOX.YIFY"},{"id":"Flow2stream_16_480","title":"Star.Wars.Episode.5.The.Empire.Strikes.Back.1980.1080p.BrRip.x264.BOKUTOX.YIFY"},{"id":"Flow2stream_16_481","title":"Star.Wars.Episode.6.Return.of.the.Jedi.1983.1080p.BrRip.x264.BOKUTOX.YIFY"},{"id":"Flow2stream_16_482","title":"Star Wars: Episode II - Attack of the Clones (2002)"},{"id":"Flow2stream_16_483","title":"Star Wars: Episode III - Revenge of the Sith (2005)"},{"id":"Flow2stream_16_484","title":"Star Wars: The Force Awakens (2015)"},{"id":"Flow2stream_16_485","title":"Star Wars: The Last Jedi (2017)"},{"id":"Flow2stream_16_486","title":"Stardog.and.Turbocat.2020.720p.WEBRip.800MB.x264-GalaxyRG"},{"id":"Flow2stream_16_487","title":"Step Up (2006)"},{"id":"Flow2stream_16_488","title":"Step Up 2 2008 The Streets"},{"id":"Flow2stream_16_489","title":"Step Up 3D (2010)"},{"id":"Flow2stream_16_490","title":"Step Up 4 2012 Revolution"},{"id":"Flow2stream_16_491","title":"Stolen (2012)"},{"id":"Flow2stream_16_492","title":"Stomp the Yard (2007)"},{"id":"Flow2stream_16_493","title":"Straight Outta Compton (2015)"},{"id":"Flow2stream_16_494","title":"Suicide Squad (2016)"},{"id":"Flow2stream_16_495","title":"Suicide Squad: Hell to Pay (2018)"},{"id":"Flow2stream_16_496","title":"Sully (2016)"},{"id":"Flow2stream_16_497","title":"Summer of 84 (2018)"},{"id":"Flow2stream_16_498","title":"Suspiria (2018)"},{"id":"Flow2stream_16_499","title":"Taken 2 (2012)"},{"id":"Flow2stream_16_500","title":"Taken (2008)"},{"id":"Flow2stream_16_501","title":"Tales from the Hood 2 (2018)"},{"id":"Flow2stream_16_502","title":"Tales from the Hood (1995)"},{"id":"Flow2stream_16_503","title":"Ted 2 (2015)"},{"id":"Flow2stream_16_504","title":"Ted (2012)"},{"id":"Flow2stream_16_505","title":"Temptation: Confessions of a Marriage Counselor (2013)"},{"id":"Flow2stream_16_506","title":"Terminator 2: Judgment Day (1991)"},{"id":"Flow2stream_16_507","title":"Terminator 3: Rise of the Machines (2003)"},{"id":"Flow2stream_16_508","title":"Terminator Genisys (2015)"},{"id":"Flow2stream_16_509","title":"Terminator Salvation (2009)"},{"id":"Flow2stream_16_510","title":"That's My Boy (2012)"},{"id":"Flow2stream_16_511","title":"The 15:17 to Paris (2018)"},{"id":"Flow2stream_16_512","title":"The 40 Year Old Virgin (2005)"},{"id":"Flow2stream_16_513","title":"The Adjustment Bureau (2011)"},{"id":"Flow2stream_16_514","title":"The Avengers (2012)"},{"id":"Flow2stream_16_515","title":"The Banker (2020)"},{"id":"Flow2stream_16_516","title":"The BFG (2016)"},{"id":"Flow2stream_16_517","title":"The Big Short (2015)"},{"id":"Flow2stream_16_518","title":"The Big Sick (2017)"},{"id":"Flow2stream_16_519","title":"The.Blackcoat's.Daughter.2015.HDRip.XViD-ETRG"},{"id":"Flow2stream_16_520","title":"The Bodyguard (1992)"},{"id":"Flow2stream_16_521","title":"The Bone Collector (1999)"},{"id":"Flow2stream_16_522","title":"The Book of Eli (2010)"},{"id":"Flow2stream_16_523","title":"The Bookshop (2017)"},{"id":"Flow2stream_16_524","title":"The Boondock Saints II: All Saints Day (2009)"},{"id":"Flow2stream_16_525","title":"The Bourne Identity (2002)"},{"id":"Flow2stream_16_526","title":"The Bourne Supremacy (2004)"},{"id":"Flow2stream_16_527","title":"The Breed (2006)"},{"id":"Flow2stream_16_528","title":"The Cloverfield Paradox (2018)"},{"id":"Flow2stream_16_529","title":"The Cobbler (2014)"},{"id":"Flow2stream_16_530","title":"The Collector (2009)"},{"id":"Flow2stream_16_531","title":"The Commuter (2018)"},{"id":"Flow2stream_16_532","title":"The Conjuring 2 (2016)"},{"id":"Flow2stream_16_533","title":"The Conjuring (2013)"},{"id":"Flow2stream_16_534","title":"The Departed (2006)"},{"id":"Flow2stream_16_535","title":"The Devil's Advocate (1997)"},{"id":"Flow2stream_16_536","title":"The Edge of Seventeen (2016)"},{"id":"Flow2stream_16_537","title":"The Evil Within (2017)"},{"id":"Flow2stream_16_538","title":"The Expendables 3 (2014)"},{"id":"Flow2stream_16_539","title":"The Expendables (2010)"},{"id":"Flow2stream_16_540","title":"The Eye (2008)"},{"id":"Flow2stream_16_541","title":"The Fate of the Furious (2017)"},{"id":"Flow2stream_16_542","title":"The First Purge (2018)"},{"id":"Flow2stream_16_543","title":"The Godfather (1972)"},{"id":"Flow2stream_16_544","title":"The Godfather: Part II (1974)"},{"id":"Flow2stream_16_545","title":"The Godfather: Part III (1990)"},{"id":"Flow2stream_16_546","title":"The Gracefield Incident (2017)"},{"id":"Flow2stream_16_547","title":"The Great Wall (2016)"},{"id":"Flow2stream_16_548","title":"The Green Hornet (2011)"},{"id":"Flow2stream_16_549","title":"The Hallow (2015)"},{"id":"Flow2stream_16_550","title":"The Happening (2008)"},{"id":"Flow2stream_16_551","title":"The House That Jack Built (2018)"},{"id":"Flow2stream_16_552","title":"The Hurricane (1999)"},{"id":"Flow2stream_16_553","title":"The Insider (1999)"},{"id":"Flow2stream_16_554","title":"The Jesus Rolls (2019)"},{"id":"Flow2stream_16_555","title":"The Last Witch Hunter (2015)"},{"id":"Flow2stream_16_556","title":"The Magnificent Seven (2016)"},{"id":"Flow2stream_16_557","title":"The Meyerowitz Stories (New and Selected) (2017)"},{"id":"Flow2stream_16_558","title":"The Pursuit of Happyness (2006)"},{"id":"Flow2stream_16_559","title":"The Ridiculous 6 (2015)"},{"id":"Flow2stream_16_560","title":"The Shining (1980)"},{"id":"Flow2stream_16_561","title":"The Single Moms Club (2014)"},{"id":"Flow2stream_16_562","title":"The Specialist (1994)"},{"id":"Flow2stream_16_563","title":"The Three Stooges (2012)"},{"id":"Flow2stream_16_564","title":"The Turning (2020)"},{"id":"Flow2stream_16_565","title":"The Waterboy (1998)"},{"id":"Flow2stream_16_566","title":"The Week Of (2018)"},{"id":"Flow2stream_16_567","title":"The Wolverine (2013)"},{"id":"Flow2stream_16_568","title":"The Animal (2001)"},{"id":"Flow2stream_16_569","title":"The Day After Tomorrow (2004)"},{"id":"Flow2stream_16_570","title":"The Do-Over (2016)"},{"id":"Flow2stream_16_571","title":"The Equalizer 2 (2018)"},{"id":"Flow2stream_16_572","title":"The Equalizer (2014)"},{"id":"Flow2stream_16_573","title":"The Foreigner (2017)"},{"id":"Flow2stream_16_574","title":"The Golden Child (1986)"},{"id":"Flow2stream_16_575","title":"The Handmaiden (2016)"},{"id":"Flow2stream_16_576","title":"The Haunting in Connecticut (2009)"},{"id":"Flow2stream_16_577","title":"The House (2017)"},{"id":"Flow2stream_16_578","title":"The Hurricane Heist (2018)"},{"id":"Flow2stream_16_579","title":"The Last House On The Left - Unrated Horror 2009 Eng Subs 1080p [H264-mp4]"},{"id":"Flow2stream_16_580","title":"The Longest Yard (2005)"},{"id":"Flow2stream_16_581","title":"The Mummy Returns (2001)"},{"id":"Flow2stream_16_582","title":"The Pelican Brief (1993)"},{"id":"Flow2stream_16_583","title":"The Ring (2002)"},{"id":"Flow2stream_16_584","title":"The Taking of Pelham 1 2 3 (2009)"},{"id":"Flow2stream_16_585","title":"The Wedding Singer (1998)"},{"id":"Flow2stream_16_586","title":"The Words (2012)"},{"id":"Flow2stream_16_587","title":"The Chronicles of Riddick (2004)"},{"id":"Flow2stream_16_588","title":"Think Like a Man Too (2014)"},{"id":"Flow2stream_16_589","title":"Third World Cop - Part 1"},{"id":"Flow2stream_16_590","title":"Third World Cop - Part 2"},{"id":"Flow2stream_16_591","title":"Titanic (1997)"},{"id":"Flow2stream_16_592","title":"Triple Frontier (2019)"},{"id":"Flow2stream_16_593","title":"Trolls World Tour (2020)"},{"id":"Flow2stream_16_594","title":"Truth or Dare (2018)"},{"id":"Flow2stream_16_595","title":"Tyler.Perry's.Madea's.Family.Reunion[2006]HiQ.DvDrip[Eng]-Ch4cal"},{"id":"Flow2stream_16_596","title":"Tyler.Perrys.A.Madea.Christmas.2013.720p.BluRay.x264.YIFY"},{"id":"Flow2stream_16_597","title":"Tyler Perry's Madea Goes To Jail"},{"id":"Flow2stream_16_598","title":"Tyler Perry's The Family that Preys 2008 DVDRip[A Release-Lounge H.264 by Titan]"},{"id":"Flow2stream_16_599","title":"Unfriended: Dark Web (2018)"},{"id":"Flow2stream_16_600","title":"Unsane (2018)"},{"id":"Flow2stream_16_601","title":"Upgrade (2018)"},{"id":"Flow2stream_16_602","title":"Velvet Buzzsaw (2019)"},{"id":"Flow2stream_16_603","title":"Waist Deep (2006)"},{"id":"Flow2stream_16_604","title":"White Men Can't Jump (1992)"},{"id":"Flow2stream_16_605","title":"Why Did I Get Married? (2007)"},{"id":"Flow2stream_16_606","title":"Why Did I Get Married Too? (2010)"},{"id":"Flow2stream_16_607","title":"Wolf (1994)"},{"id":"Flow2stream_16_608","title":"X-Men (2000)"},{"id":"Flow2stream_16_609","title":"X (2011)"},{"id":"Flow2stream_16_610","title":"X-Men Origins: Wolverine (2009)"},{"id":"Flow2stream_16_611","title":"X-Men: The Last Stand (2006)"},{"id":"Flow2stream_16_612","title":"x2.x-men.united.2003.720p.bluray.x264"},{"id":"Flow2stream_16_613","title":"xXx (2002)"},{"id":"Flow2stream_16_614","title":"xXx: Return of Xander Cage (2017)"},{"id":"Flow2stream_16_615","title":"xXx: State of the Union (2005)"},{"id":"Flow2stream_16_616","title":"You Don't Mess with the Zohan (2008)"},{"id":"Flow2stream_16_617","title":"You Don't Know Jack (2010)"},{"id":"Flow2stream_16_618","title":"Zeitgeist: Addendum (2008)"},{"id":"Flow2stream_16_619","title":"Zeitgeist (2007)"},{"id":"Flow2stream_16_620","title":"Zookeeper (2011)"},{"id":"Flow2stream_16_621","title":"Taxi 2 (2000)"},{"id":"Flow2stream_16_622","title":"Taxi 3 (2003)"},{"id":"Flow2stream_16_623","title":"Taxi 4 (2007)"},{"id":"Flow2stream_16_624","title":"Taxi (1998)"},{"id":"Flow2stream_16_625","title":"The Purge (2013)"},{"id":"Flow2stream_16_626","title":"The Purge: Anarchy (2014)"},{"id":"Flow2stream_16_627","title":"The Purge: Election Year (2016)"},{"id":"Flow2stream_16_628","title":"Tyson (1995)"},{"id":"Flow2stream_16_629","title":"Judgment Night (1993)"}]}}